{
    "input_file": "/var/lib/cwl/stg0ba23790-1f3d-4950-bb54-f5781f28793d/data.h5ad",
    "total_cells": 15458,
    "low_quality_cells": 0,
    "percent_low_quality": 0.0,
    "mean_pct_counts_mt": 0.0,
    "mean_pct_counts_ribo": 0.0,
    "thresholds": {
        "min_genes": 200,
        "max_genes": 7500,
        "max_mt": 5.0,
        "min_ribo": null,
        "mt_prefix": "MT-",
        "ribo_prefixes": [
            "RPS",
            "RPL"
        ]
    },
    "files": {
        "qc_per_cell_csv": "qc_results/qc_per_cell.csv",
        "qc_summary_csv": "qc_results/qc_summary.csv"
    }
}