{
    "input_file": "/var/lib/cwl/stg02b6f88d-7fe5-4b28-b551-5870186fa9b0/data.h5ad",
    "total_cells": 21463,
    "low_quality_cells": 498,
    "percent_low_quality": 2.32,
    "mean_pct_counts_mt": 0.0,
    "mean_pct_counts_ribo": 0.0,
    "thresholds": {
        "min_genes": 200,
        "max_genes": 7500,
        "max_mt": 5.0,
        "min_ribo": null,
        "mt_prefix": "MT-",
        "ribo_prefixes": [
            "RPS",
            "RPL"
        ]
    },
    "files": {
        "qc_per_cell_csv": "qc_results/qc_per_cell.csv",
        "qc_summary_csv": "qc_results/qc_summary.csv"
    }
}